{
  "name": "fallout.minor.fortune.unlucky.name",
  "type": "fallout",
  "system": {
    "description": "fallout.minor.fortune.unlucky.description",
    "active": false,
    "complete": false,
    "type": "minor",
    "resistance": "fortune"
  },
  "effects": [],
  "img": "icons/svg/item-bag.svg",
  "folder": "QWYnV3nvS6fFKwgj",
  "flags": {
    "core": {}
  },
  "_stats": {
    "systemId": "heart",
    "systemVersion": "<<AUTOGENERATED>>",
    "coreVersion": "11.315",
    "createdTime": 1715092412884,
    "modifiedTime": 1715376554711,
    "lastModifiedBy": "BmAk0i1zUjlVGZLo"
  },
  "_id": "4hk7If6EbD41UjMh",
  "sort": -175000,
  "ownership": {
    "default": 0,
    "BmAk0i1zUjlVGZLo": 3
  },
  "_key": "!items!4hk7If6EbD41UjMh"
}
