{
  "name": "Hell For Weather",
  "type": "fallout",
  "system": {
    "description": "fallout.major.fortune.hell_for_weather.description",
    "active": false,
    "complete": false,
    "type": "major",
    "resistance": "fortune"
  },
  "effects": [],
  "img": "icons/svg/item-bag.svg",
  "folder": null,
  "flags": {
    "core": {}
  },
  "_stats": {
    "systemId": "heart",
    "systemVersion": "<<AUTOGENERATED>>",
    "coreVersion": "11.315",
    "createdTime": 1715091886745,
    "modifiedTime": 1715092097729,
    "lastModifiedBy": "BmAk0i1zUjlVGZLo"
  },
  "_id": "T01IOeN75eiYqH0p",
  "sort": 0,
  "ownership": {
    "default": 0,
    "BmAk0i1zUjlVGZLo": 3
  },
  "_key": "!items!T01IOeN75eiYqH0p"
}
